{
    "version": "5",
    "dialect": "pg",
    "entries": [
        {
            "idx": 0,
            "version": "5",
            "when": 1706669409717,
            "tag": "0000_faithful_black_crow",
            "breakpoints": true
        },
        {
            "idx": 1,
            "version": "5",
            "when": 1706860049235,
            "tag": "0001_certain_doctor_doom",
            "breakpoints": true
        },
        {
            "idx": 2,
            "version": "5",
            "when": 1706894065676,
            "tag": "0002_adorable_nighthawk",
            "breakpoints": true
        },
        {
            "idx": 3,
            "version": "5",
            "when": 1706897331242,
            "tag": "0003_married_sumo",
            "breakpoints": true
        }
    ]
}
